LICENSE
MANIFEST.in
README.rst
requirements.txt
setup.py
src/giteway/__init__.py
src/giteway/admin.py
src/giteway/apps.py
src/giteway/models.py
src/giteway/settings.py
src/giteway/tests.py
src/giteway/utils.py
src/giteway/views.py
src/giteway.egg-info/PKG-INFO
src/giteway.egg-info/SOURCES.txt
src/giteway.egg-info/dependency_links.txt
src/giteway.egg-info/not-zip-safe
src/giteway.egg-info/requires.txt
src/giteway.egg-info/top_level.txt
src/giteway/locale/zh_Hans/LC_MESSAGES/django.mo
src/giteway/locale/zh_Hans/LC_MESSAGES/django.po
src/giteway/migrations/0001_initial.py
src/giteway/migrations/__init__.py