Metadata-Version: 1.1
Name: giteway
Version: 0.2.0
Summary: Git repos manage.
Home-page: https://github.com/appstore-zencore/giteway
Author: zencore
Author-email: appstore@zencore.cn
License: MIT
Keywords: giteway
Platform: UNKNOWN
Classifier: Development Status :: 5 - Production/Stable
Classifier: Intended Audience :: Developers
Classifier: Topic :: Software Development :: Libraries :: Python Modules
Classifier: License :: OSI Approved :: MIT License
Classifier: Programming Language :: Python :: 3
Classifier: Programming Language :: Python :: 3 :: Only
Requires: django
Requires: django_middleware_global_request
